edgechaos/__init__.py
edgechaos/client/__init__.py
edgechaos/client/api.py
edgechaos/client/factory.py
edgechaos/client/main.py
edgechaos/client/rds.py
edgechaos/client/rmq.py
edgechaos/daemon/__init__.py
edgechaos/daemon/core.py
edgechaos/daemon/run.py
edgechaos/executor/__init__.py
edgechaos/executor/api.py
edgechaos/executor/stressng.py
edgechaos/executor/tc.py
edgechaos/listeners/__init__.py
edgechaos/listeners/api.py
edgechaos/listeners/factory.py
edgechaos/listeners/rds.py
edgechaos/listeners/rmq.py
edgechaos/util/__init__.py
edgechaos/util/env.py
edgechaos/util/process.py
edgechaos/util/rds.py
edgechaos/util/rmq.py
edgerun_edge_chaos-0.0.4.dist-info/LICENSE
edgerun_edge_chaos-0.0.4.dist-info/METADATA
edgerun_edge_chaos-0.0.4.dist-info/WHEEL
edgerun_edge_chaos-0.0.4.dist-info/top_level.txt
edgerun_edge_chaos-0.0.4.dist-info/RECORD
