Metadata-Version: 2.1
Name: edgerun-edge-chaos
Version: 0.0.4
Summary: Edge Chaos
Home-page: https://github.com/edgerun/edge-chaos
Author: Philipp Raith
Author-email: p.raith@dsg.tuwien.ac.at
License: UNKNOWN
Platform: UNKNOWN
Classifier: Programming Language :: Python :: 3
Classifier: Operating System :: OS Independent
License-File: LICENSE
Requires-Dist: redis (==3.5.3)
Requires-Dist: dataclasses-json (==0.5.7)
Requires-Dist: pika (==1.3.0)
